oneTest/__init__.py
oneTest/perceptron.py
oneTest_pkg_c17hawke-0.0.9.dist-info/LICENSE
oneTest_pkg_c17hawke-0.0.9.dist-info/METADATA
oneTest_pkg_c17hawke-0.0.9.dist-info/WHEEL
oneTest_pkg_c17hawke-0.0.9.dist-info/top_level.txt
oneTest_pkg_c17hawke-0.0.9.dist-info/RECORD
