Metadata-Version: 2.1
Name: oneTest-pkg-c17hawke
Version: 0.0.9
Summary: A small example package
Home-page: https://github.com/c17hawke/oneTest
Author: c17hawke
Author-email: sunny.c17hawke@gmail.com
License: GNU
Project-URL: Bug Tracker, https://github.com/c17hawke/oneTest/issues
Platform: UNKNOWN
Requires-Python: >=3.7
License-File: LICENSE
Requires-Dist: numpy
